automatic_pypi_release/__init__.py
automatic_pypi_release/_version.py
automatic_pypi_release-1.0.0.dist-info/METADATA
automatic_pypi_release-1.0.0.dist-info/WHEEL
automatic_pypi_release-1.0.0.dist-info/top_level.txt
automatic_pypi_release-1.0.0.dist-info/RECORD
