Metadata-Version: 2.1
Name: automatic-pypi-release
Version: 1.0.0
Summary: A pip package
Home-page: UNKNOWN
Author: Felipe Espinoza
License: MIT
Platform: UNKNOWN
Classifier: Programming Language :: Python
Classifier: Programming Language :: Python :: 3.6
